[{
	"AddressTypeId": "1",
	"CustomerIdCRM": "CustomerIdCRM 1",
	"IsMainAddress": false,
	"Latitude": 4.058521030634534,
	"Longitude": 0.7041720538797636,
	"CustomerIdMD": "CustomerIdMD 1",
	"Place": {
		"PostalCode": "03103",
		"CountryID": "MX",
		"StateId": "1",
		"TownId": "132",
		"City": "DF",
		"Suburb": "Del Valle",
		"Street": "Luz Saviñon",
		"OutsideNumber": "435",
		"BetweenStreets1": "Calle A",
		"BetweenStreets2": "Calle B",
		"LocationReference": "Referencia",
		"InteriorNumber": "11",
		"Comments": "Comentarios"
	},
	"CollaboratorID": "Genesis",
	"__metadata": {
		"uri": "AddressSet(AddressTypeId='AddressTypeId%201',CustomerIdCRM='CustomerIdCRM%201')",
		"type": "AOMobile.Address"
	}
}, {
	"AddressTypeId": "2",
	"CustomerIdCRM": "CustomerIdCRM 2",
	"IsMainAddress": false,
	"Latitude": 3.088298941635259,
	"Longitude": 5.580291807654585,
	"CustomerIdMD": "CustomerIdMD 2",
	"Place": {
		"PostalCode": "62507",
		"CountryID": "MX",
		"StateId": "2",
		"TownId": "2",
		"City": "Michoacán",
		"Suburb": "Colonia",
		"Street": "Santo del Hermenegildo",
		"OutsideNumber": "810",
		"BetweenStreets1": "A",
		"BetweenStreets2": "B",
		"LocationReference": "",
		"InteriorNumber": "12",
		"Comments": ""
	},
	"CollaboratorID": "Genesis",
	"__metadata": {
		"uri": "AddressSet(AddressTypeId='AddressTypeId%202',CustomerIdCRM='CustomerIdCRM%202')",
		"type": "AOMobile.Address"
	}
}, {
	"AddressTypeId": "1",
	"CustomerIdCRM": "CustomerIdCRM 3",
	"IsMainAddress": true,
	"Latitude": 2.5758677967634735,
	"Longitude": 5.910212227745628,
	"CustomerIdMD": "CustomerIdMD 3",
	"Place": {
		"PostalCode": "01020",
		"CountryID": "MX",
		"StateId": "1",
		"TownId": "1",
		"City": "ALVARO OBREGON",
		"Suburb": "Guadalupe Inn",
		"Street": "Guty Cárdenas",
		"OutsideNumber": "48",
		"BetweenStreets1": "",
		"BetweenStreets2": "",
		"LocationReference": "",
		"InteriorNumber": "",
		"Comments": ""
	},
	"CollaboratorID": "Genesis",
	"__metadata": {
		"uri": "AddressSet(AddressTypeId='AddressTypeId%203',CustomerIdCRM='CustomerIdCRM%203')",
		"type": "AOMobile.Address"
	}
}, {
	"AddressTypeId": "3",
	"CustomerIdCRM": "CustomerIdCRM 4",
	"IsMainAddress": false,
	"Latitude": 1.010060482255557,
	"Longitude": 0.7307066653375838,
	"CustomerIdMD": "CustomerIdMD 4",
	"Place": {
		"PostalCode": "01020",
		"CountryID": "MX",
		"StateId": "1",
		"TownId": "1",
		"City": "ALVARO OBREGON",
		"Suburb": "Guadalupe Inn",
		"Street": "Caona",
		"OutsideNumber": "521",
		"BetweenStreets1": "",
		"BetweenStreets2": "",
		"LocationReference": "",
		"InteriorNumber": "",
		"Comments": ""
	},
	"CollaboratorID": "Genesis",
	"__metadata": {
		"uri": "AddressSet(AddressTypeId='AddressTypeId%204',CustomerIdCRM='CustomerIdCRM%204')",
		"type": "AOMobile.Address"
	}
}, {
	"AddressTypeId": "3",
	"CustomerIdCRM": "CustomerIdCRM 5",
	"IsMainAddress": true,
	"Latitude": 8.382364642130513,
	"Longitude": 9.586792143691142,
	"CustomerIdMD": "CustomerIdMD 5",
	"Place": {
		"PostalCode": "01020",
		"CountryID": "MX",
		"StateId": "1",
		"TownId": "1",
		"City": "ALVARO OBREGON",
		"Suburb": "Tlacopac",
		"Street": "Av. Revolución",
		"OutsideNumber": "1521",
		"BetweenStreets1": "",
		"BetweenStreets2": "",
		"LocationReference": "",
		"InteriorNumber": "",
		"Comments": ""
	},
	"CollaboratorID": "Genesis",
	"__metadata": {
		"uri": "AddressSet(AddressTypeId='AddressTypeId%205',CustomerIdCRM='CustomerIdCRM%205')",
		"type": "AOMobile.Address"
	}
}, {
	"AddressTypeId": "3",
	"CustomerIdCRM": "CustomerIdCRM 6",
	"IsMainAddress": true,
	"Latitude": 2.9563106331513866,
	"Longitude": 3.9291339932749625,
	"CustomerIdMD": "CustomerIdMD 6",
	"Place": {
		"PostalCode": "03810",
		"CountryID": "MX",
		"StateId": "1",
		"TownId": "1",
		"City": "BENITO JUAREZ",
		"Suburb": "Del Valle",
		"Street": "San Borja",
		"OutsideNumber": "908",
		"BetweenStreets1": "",
		"BetweenStreets2": "",
		"LocationReference": "",
		"InteriorNumber": "",
		"Comments": ""
	},
	"CollaboratorID": "Genesis",
	"__metadata": {
		"uri": "AddressSet(AddressTypeId='AddressTypeId%206',CustomerIdCRM='CustomerIdCRM%206')",
		"type": "AOMobile.Address"
	}
}, {
	"AddressTypeId": "2",
	"CustomerIdCRM": "CustomerIdCRM 17",
	"IsMainAddress": true,
	"Latitude": 6.309357254358217,
	"Longitude": 7.880559674384946,
	"CustomerIdMD": "CustomerIdMD 17",
	"Place": {
		"PostalCode": "03020",
		"CountryID": "MX",
		"StateId": "1",
		"TownId": "1",
		"City": "BENITO JUAREZ",
		"Suburb": "Narvarte",
		"Street": "Nicolás San Juan",
		"OutsideNumber": "327",
		"BetweenStreets1": "",
		"BetweenStreets2": "",
		"LocationReference": "",
		"InteriorNumber": "",
		"Comments": ""
	},
	"CollaboratorID": "Genesis",
	"__metadata": {
		"uri": "AddressSet(AddressTypeId='AddressTypeId%207',CustomerIdCRM='CustomerIdCRM%207')",
		"type": "AOMobile.Address"
	}
},{
	"AddressTypeId": "2",
	"CustomerIdCRM": "CustomerIdCRM 7",
	"IsMainAddress": true,
	"Latitude": 6.309357254358217,
	"Longitude": 7.880559674384946,
	"CustomerIdMD": "CustomerIdMD 7",
	"Place": {
		"PostalCode": "03020",
		"CountryID": "MX",
		"StateId": "1",
		"TownId": "1",
		"City": "BENITO JUAREZ",
		"Suburb": "Narvarte",
		"Street": "Nicolás San Juan",
		"OutsideNumber": "327",
		"BetweenStreets1": "",
		"BetweenStreets2": "",
		"LocationReference": "",
		"InteriorNumber": "",
		"Comments": ""
	},
	"CollaboratorID": "Genesis",
	"__metadata": {
		"uri": "AddressSet(AddressTypeId='AddressTypeId%207',CustomerIdCRM='CustomerIdCRM%207')",
		"type": "AOMobile.Address"
	}
}, {
	"AddressTypeId": "XXDEFAULT",
	"CustomerIdCRM": "1502388100257",
	"IsMainAddress": true,
	"Latitude": 7.895034589700094,
	"Longitude": 4.878470654359899,
	"CustomerIdMD": "CustomerIdMD 8",
	"Place": {
		"PostalCode": "03100",
		"CountryID": "MX",
		"StateId": "1",
		"TownId": "1",
		"City": "BENITO JUAREZ",
		"Suburb": "Del Valle",
		"Street": "Manzanas",
		"OutsideNumber": "56",
		"BetweenStreets1": "",
		"BetweenStreets2": "",
		"LocationReference": "",
		"InteriorNumber": "11",
		"Comments": ""
	},
	"CollaboratorID": "Genesis",
	"__metadata": {
		"uri": "AddressSet(AddressTypeId='AddressTypeId%208',CustomerIdCRM='CustomerIdCRM%208')",
		"type": "AOMobile.Address"
	}
}, {
	"AddressTypeId": "3",
	"CustomerIdCRM": "1502388083933",
	"IsMainAddress": true,
	"Latitude": 8.97072345543801,
	"Longitude": 0.8941156777266057,
	"CustomerIdMD": "CustomerIdMD 9",
	"Place": {
		"PostalCode": "03100",
		"CountryID": "MX",
		"StateId": "1",
		"TownId": "1",
		"City": "BENITO JUAREZ",
		"Suburb": "Del Valle",
		"Street": "San Francisco",
		"OutsideNumber": "419",
		"BetweenStreets1": "",
		"BetweenStreets2": "",
		"LocationReference": "",
		"InteriorNumber": "",
		"Comments": ""
	},
	"CollaboratorID": "Genesis",
	"__metadata": {
		"uri": "AddressSet(AddressTypeId='AddressTypeId%209',CustomerIdCRM='CustomerIdCRM%209')",
		"type": "AOMobile.Address"
	}
}, {
	"AddressTypeId": "XXDEFAULT",
	"CustomerIdCRM": "1502387967222",
	"IsMainAddress": true,
	"Latitude": 9.305614964082734,
	"Longitude": 0.1997572227443678,
	"CustomerIdMD": "CustomerIdMD 10",
	"Place": {
		"PostalCode": "03020",
		"CountryID": "MX",
		"StateId": "XXDEFAULT",
		"TownId": "1",
		"City": "BENITO JUAREZ",
		"Suburb": "Narvarte",
		"Street": " Av. Universidad",
		"OutsideNumber": "473",
		"BetweenStreets1": "",
		"BetweenStreets2": "",
		"LocationReference": "",
		"InteriorNumber": "",
		"Comments": ""
	},
	"CollaboratorID": "Genesis",
	"__metadata": {
		"uri": "AddressSet(AddressTypeId='AddressTypeId%2010',CustomerIdCRM='CustomerIdCRM%2010')",
		"type": "AOMobile.Address"
	}
}, {
	"AddressTypeId": "2",
	"CustomerIdCRM": "1502388048659",
	"IsMainAddress": true,
	"Latitude": 9.305614964082734,
	"Longitude": 0.1997572227443678,
	"CustomerIdMD": "CustomerIdMD 10",
	"Place": {
		"PostalCode": "03020",
		"CountryID": "MX",
		"StateId": "1",
		"TownId": "1",
		"City": "BENITO JUAREZ",
		"Suburb": "Narvarte",
		"Street": " Av. Universidad",
		"OutsideNumber": "473",
		"BetweenStreets1": "",
		"BetweenStreets2": "",
		"LocationReference": "",
		"InteriorNumber": "",
		"Comments": ""
	},
	"CollaboratorID": "Genesis",
	"__metadata": {
		"uri": "AddressSet(AddressTypeId='AddressTypeId%2010',CustomerIdCRM='CustomerIdCRM%2010')",
		"type": "AOMobile.Address"
	}
},{
	"AddressTypeId": "XXDEFAULT",
	"CustomerIdCRM": "1502388071147",
	"IsMainAddress": true,
	"Latitude": 9.305614964082734,
	"Longitude": 0.1997572227443678,
	"CustomerIdMD": "CustomerIdMD 10",
	"Place": {
		"PostalCode": "03020",
		"CountryID": "MX",
		"StateId": "1",
		"TownId": "1",
		"City": "BENITO JUAREZ",
		"Suburb": "Narvarte",
		"Street": " Av. Universidad",
		"OutsideNumber": "473",
		"BetweenStreets1": "",
		"BetweenStreets2": "",
		"LocationReference": "",
		"InteriorNumber": "",
		"Comments": ""
	},
	"CollaboratorID": "Genesis",
	"__metadata": {
		"uri": "AddressSet(AddressTypeId='AddressTypeId%2010',CustomerIdCRM='CustomerIdCRM%2010')",
		"type": "AOMobile.Address"
	}
},{
	"AddressTypeId": "XXDEFAULT",
	"CustomerIdCRM": "1502388100300",
	"IsMainAddress": true,
	"Latitude": 9.305614964082734,
	"Longitude": 0.1997572227443678,
	"CustomerIdMD": "CustomerIdMD 10",
	"Place": {
		"PostalCode": "03020",
		"CountryID": "MX",
		"StateId": "1",
		"TownId": "1",
		"City": "BENITO JUAREZ",
		"Suburb": "Narvarte",
		"Street": " Av. Universidad",
		"OutsideNumber": "473",
		"BetweenStreets1": "",
		"BetweenStreets2": "",
		"LocationReference": "",
		"InteriorNumber": "",
		"Comments": ""
	},
	"CollaboratorID": "Genesis",
	"__metadata": {
		"uri": "AddressSet(AddressTypeId='AddressTypeId%2011',CustomerIdCRM='CustomerIdCRM%2011')",
		"type": "AOMobile.Address"
	}
}]