[{
	"PreLoanRequestID": "c8d09f89-b73b-478d-a4b0-5b3a11388a07",
	"LoanRequestIdCRM": "LoanRequestIdCRM 1",
	"CollaboratorID": "DVALENCIA",
	"ServiceOfficeId": 5076,
	"StatusId": "StatusId 1",
	"CreationDate": "/Date(1206648557000)/",
	"ChangeDate": "/Date(1308424157000)/",
	"LoanEndDate": "/Date(1411844957000)/",
	"LoanAssignedName": "LoanAssignedName 1",
	"IsRenovation": false,
	"LoanRequestIdMD": "LoanRequestIdMD 1",
	"ProcessType": "ProcessType 1",
	"LoanRejectIdCatalog": "LoanRejectIdCatalog 1",
	"__metadata": {
		"uri": "PreLoanRequestSet(guid'c8d09f89-b73b-478d-a4b0-5b3a11388a07')",
		"type": "AOMobile.PreLoanRequest"
	},
	"LinkPreloanRequestSet": {
		"__deferred": {
			"uri": "PreLoanRequestSet(guid'c8d09f89-b73b-478d-a4b0-5b3a11388a07')/LinkPreloanRequestSet"
		}
	}
}, {
	"PreLoanRequestID": "2fc8b0fd-7d29-4382-80c6-f2768f0ad336",
	"LoanRequestIdCRM": "LoanRequestIdCRM 2",
	"CollaboratorID": "CollaboratorID 2",
	"ServiceOfficeId": 679,
	"StatusId": "StatusId 2",
	"CreationDate": "/Date(1263154157000)/",
	"ChangeDate": "/Date(1031166557000)/",
	"LoanEndDate": "/Date(1523732957000)/",
	"LoanAssignedName": "LoanAssignedName 2",
	"IsRenovation": false,
	"LoanRequestIdMD": "LoanRequestIdMD 2",
	"ProcessType": "ProcessType 2",
	"LoanRejectIdCatalog": "LoanRejectIdCatalog 2",
	"__metadata": {
		"uri": "PreLoanRequestSet(guid'2fc8b0fd-7d29-4382-80c6-f2768f0ad336')",
		"type": "AOMobile.PreLoanRequest"
	},
	"LinkPreloanRequestSet": {
		"__deferred": {
			"uri": "PreLoanRequestSet(guid'2fc8b0fd-7d29-4382-80c6-f2768f0ad336')/LinkPreloanRequestSet"
		}
	}
}, {
	"PreLoanRequestID": "fee98ecd-6356-4955-8445-d5fbbd25569a",
	"LoanRequestIdCRM": "LoanRequestIdCRM 3",
	"CollaboratorID": "CollaboratorID 3",
	"ServiceOfficeId": 870,
	"StatusId": "StatusId 3",
	"CreationDate": "/Date(965675357000)/",
	"ChangeDate": "/Date(1157742557000)/",
	"LoanEndDate": "/Date(956862557000)/",
	"LoanAssignedName": "LoanAssignedName 3",
	"IsRenovation": false,
	"LoanRequestIdMD": "LoanRequestIdMD 3",
	"ProcessType": "ProcessType 3",
	"LoanRejectIdCatalog": "LoanRejectIdCatalog 3",
	"__metadata": {
		"uri": "PreLoanRequestSet(guid'fee98ecd-6356-4955-8445-d5fbbd25569a')",
		"type": "AOMobile.PreLoanRequest"
	},
	"LinkPreloanRequestSet": {
		"__deferred": {
			"uri": "PreLoanRequestSet(guid'fee98ecd-6356-4955-8445-d5fbbd25569a')/LinkPreloanRequestSet"
		}
	}
}, {
	"PreLoanRequestID": "65611d72-8cf9-49c5-88a2-d9b3ae8ead8e",
	"LoanRequestIdCRM": "LoanRequestIdCRM 4",
	"CollaboratorID": "CollaboratorID 4",
	"ServiceOfficeId": 1377,
	"StatusId": "StatusId 4",
	"CreationDate": "/Date(1351454957000)/",
	"ChangeDate": "/Date(1515442157000)/",
	"LoanEndDate": "/Date(1313780957000)/",
	"LoanAssignedName": "LoanAssignedName 4",
	"IsRenovation": true,
	"LoanRequestIdMD": "LoanRequestIdMD 4",
	"ProcessType": "ProcessType 4",
	"LoanRejectIdCatalog": "LoanRejectIdCatalog 4",
	"__metadata": {
		"uri": "PreLoanRequestSet(guid'65611d72-8cf9-49c5-88a2-d9b3ae8ead8e')",
		"type": "AOMobile.PreLoanRequest"
	},
	"LinkPreloanRequestSet": {
		"__deferred": {
			"uri": "PreLoanRequestSet(guid'65611d72-8cf9-49c5-88a2-d9b3ae8ead8e')/LinkPreloanRequestSet"
		}
	}
}, {
	"PreLoanRequestID": "2740dc06-0be0-4cd3-82c6-5cec3e262f47",
	"LoanRequestIdCRM": "LoanRequestIdCRM 5",
	"CollaboratorID": "CollaboratorID 5",
	"ServiceOfficeId": 4538,
	"StatusId": "StatusId 5",
	"CreationDate": "/Date(1472065757000)/",
	"ChangeDate": "/Date(1370632157000)/",
	"LoanEndDate": "/Date(1047672557000)/",
	"LoanAssignedName": "LoanAssignedName 5",
	"IsRenovation": true,
	"LoanRequestIdMD": "LoanRequestIdMD 5",
	"ProcessType": "ProcessType 5",
	"LoanRejectIdCatalog": "LoanRejectIdCatalog 5",
	"__metadata": {
		"uri": "PreLoanRequestSet(guid'2740dc06-0be0-4cd3-82c6-5cec3e262f47')",
		"type": "AOMobile.PreLoanRequest"
	},
	"LinkPreloanRequestSet": {
		"__deferred": {
			"uri": "PreLoanRequestSet(guid'2740dc06-0be0-4cd3-82c6-5cec3e262f47')/LinkPreloanRequestSet"
		}
	}
}, {
	"PreLoanRequestID": "1dce0593-a958-448d-ab8a-0125705223ef",
	"LoanRequestIdCRM": "LoanRequestIdCRM 6",
	"CollaboratorID": "CollaboratorID 6",
	"ServiceOfficeId": 6511,
	"StatusId": "StatusId 6",
	"CreationDate": "/Date(1352664557000)/",
	"ChangeDate": "/Date(1538420957000)/",
	"LoanEndDate": "/Date(950990957000)/",
	"LoanAssignedName": "LoanAssignedName 6",
	"IsRenovation": true,
	"LoanRequestIdMD": "LoanRequestIdMD 6",
	"ProcessType": "ProcessType 6",
	"LoanRejectIdCatalog": "LoanRejectIdCatalog 6",
	"__metadata": {
		"uri": "PreLoanRequestSet(guid'1dce0593-a958-448d-ab8a-0125705223ef')",
		"type": "AOMobile.PreLoanRequest"
	},
	"LinkPreloanRequestSet": {
		"__deferred": {
			"uri": "PreLoanRequestSet(guid'1dce0593-a958-448d-ab8a-0125705223ef')/LinkPreloanRequestSet"
		}
	}
}, {
	"PreLoanRequestID": "e0edeafc-2ab9-41b0-a73b-84d314caf207",
	"LoanRequestIdCRM": "LoanRequestIdCRM 7",
	"CollaboratorID": "CollaboratorID 7",
	"ServiceOfficeId": 2077,
	"StatusId": "StatusId 7",
	"CreationDate": "/Date(1219864157000)/",
	"ChangeDate": "/Date(1278011357000)/",
	"LoanEndDate": "/Date(1168718957000)/",
	"LoanAssignedName": "LoanAssignedName 7",
	"IsRenovation": false,
	"LoanRequestIdMD": "LoanRequestIdMD 7",
	"ProcessType": "ProcessType 7",
	"LoanRejectIdCatalog": "LoanRejectIdCatalog 7",
	"__metadata": {
		"uri": "PreLoanRequestSet(guid'e0edeafc-2ab9-41b0-a73b-84d314caf207')",
		"type": "AOMobile.PreLoanRequest"
	},
	"LinkPreloanRequestSet": {
		"__deferred": {
			"uri": "PreLoanRequestSet(guid'e0edeafc-2ab9-41b0-a73b-84d314caf207')/LinkPreloanRequestSet"
		}
	}
}, {
	"PreLoanRequestID": "3a3924a7-d568-46c5-b101-c663f16a1416",
	"LoanRequestIdCRM": "LoanRequestIdCRM 8",
	"CollaboratorID": "CollaboratorID 8",
	"ServiceOfficeId": 7837,
	"StatusId": "StatusId 8",
	"CreationDate": "/Date(1174334957000)/",
	"ChangeDate": "/Date(1159902557000)/",
	"LoanEndDate": "/Date(953842157000)/",
	"LoanAssignedName": "LoanAssignedName 8",
	"IsRenovation": false,
	"LoanRequestIdMD": "LoanRequestIdMD 8",
	"ProcessType": "ProcessType 8",
	"LoanRejectIdCatalog": "LoanRejectIdCatalog 8",
	"__metadata": {
		"uri": "PreLoanRequestSet(guid'3a3924a7-d568-46c5-b101-c663f16a1416')",
		"type": "AOMobile.PreLoanRequest"
	},
	"LinkPreloanRequestSet": {
		"__deferred": {
			"uri": "PreLoanRequestSet(guid'3a3924a7-d568-46c5-b101-c663f16a1416')/LinkPreloanRequestSet"
		}
	}
}, {
	"PreLoanRequestID": "c867bdb3-3c35-4e0a-806c-702c79ad71ef",
	"LoanRequestIdCRM": "LoanRequestIdCRM 9",
	"CollaboratorID": "CollaboratorID 9",
	"ServiceOfficeId": 2716,
	"StatusId": "StatusId 9",
	"CreationDate": "/Date(1149102557000)/",
	"ChangeDate": "/Date(1265314157000)/",
	"LoanEndDate": "/Date(1134245357000)/",
	"LoanAssignedName": "LoanAssignedName 9",
	"IsRenovation": true,
	"LoanRequestIdMD": "LoanRequestIdMD 9",
	"ProcessType": "ProcessType 9",
	"LoanRejectIdCatalog": "LoanRejectIdCatalog 9",
	"__metadata": {
		"uri": "PreLoanRequestSet(guid'c867bdb3-3c35-4e0a-806c-702c79ad71ef')",
		"type": "AOMobile.PreLoanRequest"
	},
	"LinkPreloanRequestSet": {
		"__deferred": {
			"uri": "PreLoanRequestSet(guid'c867bdb3-3c35-4e0a-806c-702c79ad71ef')/LinkPreloanRequestSet"
		}
	}
}, {
	"PreLoanRequestID": "81f1bcb5-3289-40ca-8b2d-5cacc31c5056",
	"LoanRequestIdCRM": "LoanRequestIdCRM 10",
	"CollaboratorID": "CollaboratorID 10",
	"ServiceOfficeId": 4706,
	"StatusId": "StatusId 10",
	"CreationDate": "/Date(1035140957000)/",
	"ChangeDate": "/Date(1029352157000)/",
	"LoanEndDate": "/Date(1508872157000)/",
	"LoanAssignedName": "LoanAssignedName 10",
	"IsRenovation": false,
	"LoanRequestIdMD": "LoanRequestIdMD 10",
	"ProcessType": "ProcessType 10",
	"LoanRejectIdCatalog": "LoanRejectIdCatalog 10",
	"__metadata": {
		"uri": "PreLoanRequestSet(guid'81f1bcb5-3289-40ca-8b2d-5cacc31c5056')",
		"type": "AOMobile.PreLoanRequest"
	},
	"LinkPreloanRequestSet": {
		"__deferred": {
			"uri": "PreLoanRequestSet(guid'81f1bcb5-3289-40ca-8b2d-5cacc31c5056')/LinkPreloanRequestSet"
		}
	}
}]