[{
	"PreLoanRequestID": "dc897c8e-5e0e-4acd-b210-c39000cfcb94",
	"LoanRequestIdCRM": "LoanRequestIdCRM 1",
	"CollaboratorID": "Genesis",
	"ServiceOfficeId": 767,
	"StatusId": "StatusId 1",
	"CreationDate": "/Date(957996037000)/",
	"ChangeDate": "/Date(1306447237000)/",
	"LoanEndDate": "/Date(1219874437000)/",
	"LoanAssignedName": "RAMIRO RAMÓN ROBLES",
	"IsRenovation": false,
	"LoanRequestIdMD": "LoanRequestIdMD 1",
	"ProcessType": "ZOPI",
	"LoanRejectIdCatalog": "",
	"__metadata": {
		"uri": "PreLoanRequestSet(guid'dc897c8e-5e0e-4acd-b210-c39000cfcb94')",
		"type": "AOMobile.PreLoanRequest"
	},
	"LinkPreloanRequestSet": {
		"__deferred": {
			"uri": "PreLoanRequestSet(guid'dc897c8e-5e0e-4acd-b210-c39000cfcb94')/LinkPreloanRequestSet"
		}
	}
}, {
	"PreLoanRequestID": "db316aa1-6465-465f-9a22-47a34d0791f5",
	"LoanRequestIdCRM": "LoanRequestIdCRM 1",
	"CollaboratorID": "Genesis",
	"ServiceOfficeId": 7380,
	"StatusId": "StatusId 2",
	"CreationDate": "/Date(1459292437000)/",
	"ChangeDate": "/Date(1057528837000)/",
	"LoanEndDate": "/Date(1447628437000)/",
	"LoanAssignedName": "GRUPO A",
	"IsRenovation": true,
	"LoanRequestIdMD": "LoanRequestIdMD 1",
	"ProcessType": "ZOPG",
	"LoanRejectIdCatalog": "",
	"__metadata": {
		"uri": "PreLoanRequestSet(guid'db316aa1-6465-465f-9a22-47a34d0791f5')",
		"type": "AOMobile.PreLoanRequest"
	},
	"LinkPreloanRequestSet": {
		"__deferred": {
			"uri": "PreLoanRequestSet(guid'db316aa1-6465-465f-9a22-47a34d0791f5')/LinkPreloanRequestSet"
		}
	}
}]